<?xml version="1.0" encoding="UTF-8"?>
<?xml-stylesheet type="text/xsl" href="../../hino.xsl"?>
<hino situacao="incompleto">
  <numero>035</numero>
  <n>35</n>
  <titulo>Adoração e Súplica</titulo>
  <texto>
    <estrofe>
      <verso>Teu culto agora, aqui, Senhor,</verso>
      <verso>Nós vimos celebrar,</verso>
      <verso>Cantando, juntos, teu louvor,</verso>
      <verso>Teu livro a meditar.</verso>
    </estrofe>
    <estrofe>
      <verso>À nossa vera adoração</verso>
      <verso>Presente estás, Senhor,</verso>
      <verso>Fazendo o nosso coração</verso>
      <verso>Sentir teu grande amor.</verso>
    </estrofe>
    <estrofe>
      <verso>Atende nossas petições,</verso>
      <verso>Ó poderoso Deus!</verso>
      <verso>Concede aos nossos corações</verso>
      <verso>Antegozar os céus. </verso>
      <verso>Amém.</verso>
    </estrofe>
  </texto>
  <secao id="01">Louvor e Adoração</secao>
  <assunto id="08">Deus Senhor</assunto>
  <origem_letra>J. Th. Houston</origem_letra>
</hino>