<?xml version="1.0" encoding="UTF-8"?>
<?xml-stylesheet type="text/xsl" href="../../hino.xsl"?>
<hino>
  <numero>135</numero>
  <n>135</n>
  <titulo>Mais de Cristo</titulo>
  <texto>
    <estrofe>
      <verso>Mais de Cristo eu quero ter,</verso>
      <verso>Seu ensino receber,</verso>
      <verso>Ter da sua compaixão</verso>
      <verso>E da sua mansidão.</verso>
      <coro>
        <verso>Mais,mais de Cristo!</verso>
        <verso>Mais,mais de Cristo!</verso>
        <verso>Mais do seu puro e santo amor</verso>
        <verso>Mais do bondoso Salvador.</verso>
      </coro>
    </estrofe>
    <estrofe>
      <verso>Mais de Cristo eu quero ouvir</verso>
      <verso>Nos seu passos prosseguir,</verso>
      <verso>Sempre perto dele andar,</verso>
      <verso>Seu amor manifestar.</verso>
    </estrofe>
  </texto>
  <secao id="03">Edificação</secao>
  <assunto id="11">Santificação</assunto>
  <titulo_original>More About Jesus</titulo_original>
  <metrica id="7_7_7_7_Coro">7.7.7.7.Coro</metrica>
  <origem_letra id="HewittEE" referencia="Hewitt, Eliza Edmunds">Eliza Edmunds Hewitt</origem_letra>
  <origem_letra id="WrightHM" referencia="Wright, Henry Maxwell" ano="1900">Henry Maxwell Wright</origem_letra>
  <origem_musica id="SweneyJR" referencia="Sweney, John Robson">John Robson Sweney</origem_musica>
  <primeiro_verso_original>Mais de Cristo eu quero ter</primeiro_verso_original>
  <referencia_biblica id="28_006_003">Oséias 6.3</referencia_biblica>
</hino>
