<hino situacao='incompleto'>
    <numero>214</numero>
    <n>214</n>
    <titulo>Convite e aceitação</titulo>
    <texto>
      <estrofe>
        <verso>Ouço meu Senhor dizer:</verso>
        <verso>“Tuas forças débeis são,</verso>
        <verso>Nada podes merecer;</verso>
        <verso>Eu te dou a salvação.</verso>
        <coro>
          <verso>A ti, Senhor Jesus,</verso>
          <verso>Venho como estou;</verso>
          <verso>Pois sem nada merecer,</verso>
          <verso>Teu sangue me salvou.</verso>
        </coro>
      </estrofe>
      <estrofe>
        <verso>Sim, eu venho a ti, Senhor,</verso>
        <verso>Tua graça receber;</verso>
        <verso>Infinito é o teu amor,</verso>
        <verso>Sem limite o teu poder.</verso>
      </estrofe>
      <estrofe>
        <verso>Quando estou em aflições,</verso>
        <verso>Tu és meu Consolador;</verso>
        <verso>Quando exposto às tentações,</verso>
        <verso>Meu auxílio e protetor.</verso>
      </estrofe>
      <estrofe>
        <verso>Lá na glória cantarei</verso>
        <verso>Tua eterna salvação;</verso>
        <verso>Junto ao trono renderei</verso>
        <verso>Meu louvor e gratidão. Amém.</verso>
      </estrofe>
    </texto>
    <secao id=''/>
    <assunto id=''/>
    <titulo_original/>
    <metrica id=''/>
    <origem_letra ano='' id='' referencia=''/>
    <origem_musica ano='' id='' referencia=''/>
    <primeiro_verso_original/>
    <referencia_biblica id=''/>
  </hino>