<hino situacao='incompleto'>
    <numero>246</numero>
    <n>246</n>
    <titulo>Jesus, o Messias</titulo>
    <texto>
      <estrofe>
        <verso>Jesus, o Messias, desceu lá do céu,</verso>
        <verso>E foi no Natal quando ao mundo nasceu.</verso>
        <verso>Alegre e feliz eu me devo sentir,</verso>
        <verso>Pois ele é o bem Rei que nos veio remir.</verso>
      </estrofe>
      <estrofe>
        <verso>Jesus, o messias, não quis aqui ter</verso>
        <verso>Um berço macio e na vida prazer!</verso>
        <verso>Mas na manjedoura nasceu meu Jesus</verso>
        <verso>Quando ele nos veio trazer vida e luz</verso>
      </estrofe>
      <estrofe>
        <verso>Jesus, o Messias, que veio salvar,</verso>
        <verso>A paz já nos deu e com Deu foi estar.</verso>
        <verso>E neste Natal, abençoa, Senhor,</verso>
        <verso>As vidas que agora te rendem louvor. Amém.</verso>
      </estrofe>
    </texto>
    <secao id=''/>
    <assunto id=''/>
    <titulo_original/>
    <metrica id=''/>
    <origem_letra ano='' id='' referencia=''/>
    <origem_musica ano='' id='' referencia=''/>
    <primeiro_verso_original/>
    <referencia_biblica id=''/>
  </hino>