<?xml version="1.0" encoding="UTF-8"?>
<?xml-stylesheet type="text/xsl" href="../../hino.xsl"?>
<hino>
  <numero>327</numero>
  <n>327</n>
  <titulo>Obreiros cristãos</titulo>
  <texto>
    <estrofe>
      <verso>Aqui reunidos, queremos, ó Deus,</verso>
      <verso>À causa da Igreja servir.</verso>
      <verso>Na santa seara, a nós, servos teus,</verso>
      <verso>Oh, mostra, Senhor, como agir.</verso>
      <verso>Aos teus mensageiros, oh, vem, Salvador,</verso>
      <verso>Tornar cada vez mais fiéis!</verso>
      <verso>E dá-lhes amparo e sustento, Senhor,</verso>
      <verso>Em tempos tão maus e cruéis.</verso>
    </estrofe>
    <estrofe>
      <verso>Nas lutas, liberta-os de toda paixão</verso>
      <verso>E dá-lhes o amor eficaz,</verso>
      <verso>O amor que congraça, que faz a união,</verso>
      <verso>O amor do “Evangelho da Paz.”</verso>
      <verso>De vis preconceitos e impulsos carnais</verso>
      <verso>Vem sempre os teus servos guardar,</verso>
      <verso>Unindo-os no afeto de amigos leais,</verso>
    </estrofe>
    <estrofe>
      <verso>Fazendo-os em paz trabalhar.</verso>
      <verso>Oh, dá às mensagens mais alto poder;</verso>
      <verso>A todos inspira na cruz!</verso>
      <verso>Senhor, aos teus servos concede o saber,</verso>
      <verso>Mais fé, mais lampejos de luz!</verso>
      <verso>Dos falsos obreiros a astúcia do mal</verso>
      <verso>Afasta, Senhor, com poder.</verso>
      <verso>E à boa semente do santo trigal</verso>
      <verso>Permite nascer e crescer! Amém.</verso>
    </estrofe>
  </texto>
  <secao id="07">Igreja - Seu Ministério</secao>
  <assunto id="06">Discipulado e Serviço</assunto>
  <titulo_original>Consecration</titulo_original>
  <metrica id="11_8_11_8_D__D_">11.8.11.8.D.[D]</metrica>
  <origem_letra id="GueirosJ" referencia="Gueiros, Jerônimo">Jerônimo Gueiros</origem_letra>
  <origem_musica id="RounsefellCEP" referencia="Rounsefell, Carrie Esther Parker" ano="1894">Carrie Esther Parker Rounsefell</origem_musica>
  <primeiro_verso_original>Aqui reunidos, queremos, ó Deus</primeiro_verso_original>
  <referencia_biblica id="40_013_030">Mateus 13.30</referencia_biblica>
</hino>

